monsql/__init__.py
monsql_ninja-1.0.0.dist-info/LICENSE
monsql_ninja-1.0.0.dist-info/METADATA
monsql_ninja-1.0.0.dist-info/WHEEL
monsql_ninja-1.0.0.dist-info/top_level.txt
monsql_ninja-1.0.0.dist-info/RECORD
