Metadata-Version: 2.1
Name: monsql-ninja
Version: 1.0.0
Summary: The French MySQL wrapper in Python
Home-page: https://github.com/MaitreRenard/MonSQL-python
Author: Masterfox, 0xNinja, Apollo
Author-email: 0xNinja <57400445+OxNinja@users.noreply.github.com>, MasterFox <tom.mounet@pm.me>, Apollo <noreply@github.com>
License: GNU GENERAL PUBLIC LICENSE
Project-URL: Homepage, https://github.com/maitrerenard/MonSQL-python
Keywords: mysql,monsql,database
Classifier: License :: OSI Approved :: GNU General Public License v3 (GPLv3)
Classifier: Programming Language :: Python
Classifier: Programming Language :: Python :: 3
Requires-Python: >=3.6
License-File: LICENSE
Requires-Dist: mysql-connector-python
